upset_plot/__init__.py
upset_plot/core.py
upset_plot_plotly-0.2.2.dist-info/METADATA
upset_plot_plotly-0.2.2.dist-info/WHEEL
upset_plot_plotly-0.2.2.dist-info/top_level.txt
upset_plot_plotly-0.2.2.dist-info/RECORD
