Metadata-Version: 2.4
Name: upset_plot_plotly
Version: 0.2.2
Summary: A generic and colored Upset Plot generator using Plotly
Author: Prabin Raj KP
Classifier: Programming Language :: Python :: 3
Classifier: License :: OSI Approved :: MIT License
Classifier: Operating System :: OS Independent
Requires-Python: >=3.6
Requires-Dist: pandas
Requires-Dist: plotly
Dynamic: author
Dynamic: classifier
Dynamic: description
Dynamic: description-content-type
Dynamic: requires-dist
Dynamic: requires-python
Dynamic: summary
